GowebKaifaShizhanBeegoKuangjiaShixianXiangmu/README.md
GowebKaifaShizhanBeegoKuangjiaShixianXiangmu/__init__.py
GowebKaifaShizhanBeegoKuangjiaShixianXiangmu/__main__.py
GowebKaifaShizhanBeegoKuangjiaShixianXiangmu/file.epub
GowebKaifaShizhanBeegoKuangjiaShixianXiangmu/index.html
GowebKaifaShizhanBeegoKuangjiaShixianXiangmu/css/__init__.py
GowebKaifaShizhanBeegoKuangjiaShixianXiangmu/css/annotations.css
GowebKaifaShizhanBeegoKuangjiaShixianXiangmu/css/main.css
GowebKaifaShizhanBeegoKuangjiaShixianXiangmu/css/normalize.css
GowebKaifaShizhanBeegoKuangjiaShixianXiangmu/css/popup.css
GowebKaifaShizhanBeegoKuangjiaShixianXiangmu/font/__init__.py
GowebKaifaShizhanBeegoKuangjiaShixianXiangmu/font/fontello.eot
GowebKaifaShizhanBeegoKuangjiaShixianXiangmu/font/fontello.svg
GowebKaifaShizhanBeegoKuangjiaShixianXiangmu/font/fontello.ttf
GowebKaifaShizhanBeegoKuangjiaShixianXiangmu/font/fontello.woff
GowebKaifaShizhanBeegoKuangjiaShixianXiangmu/img/__init__.py
GowebKaifaShizhanBeegoKuangjiaShixianXiangmu/img/annotator-glyph-sprite.png
GowebKaifaShizhanBeegoKuangjiaShixianXiangmu/img/annotator-icon-sprite.png
GowebKaifaShizhanBeegoKuangjiaShixianXiangmu/img/apple-touch-icon.png
GowebKaifaShizhanBeegoKuangjiaShixianXiangmu/img/cancelfullscreen.png
GowebKaifaShizhanBeegoKuangjiaShixianXiangmu/img/close.png
GowebKaifaShizhanBeegoKuangjiaShixianXiangmu/img/fullscreen.png
GowebKaifaShizhanBeegoKuangjiaShixianXiangmu/img/loader.gif
GowebKaifaShizhanBeegoKuangjiaShixianXiangmu/img/menu-icon.png
GowebKaifaShizhanBeegoKuangjiaShixianXiangmu/img/save.png
GowebKaifaShizhanBeegoKuangjiaShixianXiangmu/img/saved.png
GowebKaifaShizhanBeegoKuangjiaShixianXiangmu/img/settings-s.png
GowebKaifaShizhanBeegoKuangjiaShixianXiangmu/img/settings.png
GowebKaifaShizhanBeegoKuangjiaShixianXiangmu/img/star.png
GowebKaifaShizhanBeegoKuangjiaShixianXiangmu/js/__init__.py
GowebKaifaShizhanBeegoKuangjiaShixianXiangmu/js/epub.js
GowebKaifaShizhanBeegoKuangjiaShixianXiangmu/js/epub.min.js
goweb_kaifa_shizhan_beego_kuangjia_shixian_xiangmu-2024.3.5.0.dist-info/METADATA
goweb_kaifa_shizhan_beego_kuangjia_shixian_xiangmu-2024.3.5.0.dist-info/WHEEL
goweb_kaifa_shizhan_beego_kuangjia_shixian_xiangmu-2024.3.5.0.dist-info/entry_points.txt
goweb_kaifa_shizhan_beego_kuangjia_shixian_xiangmu-2024.3.5.0.dist-info/top_level.txt
goweb_kaifa_shizhan_beego_kuangjia_shixian_xiangmu-2024.3.5.0.dist-info/RECORD
